smallaxe/__init__.py
smallaxe/_config.py
smallaxe/auto/__init__.py
smallaxe/datasets/__init__.py
smallaxe/datasets/_data.py
smallaxe/exceptions/__init__.py
smallaxe/metrics/__init__.py
smallaxe/metrics/classification.py
smallaxe/metrics/regression.py
smallaxe/pipeline/__init__.py
smallaxe/pipeline/pipeline.py
smallaxe/preprocessing/__init__.py
smallaxe/preprocessing/encoder.py
smallaxe/preprocessing/imputer.py
smallaxe/preprocessing/scaler.py
smallaxe/search/__init__.py
smallaxe/training/__init__.py
smallaxe/training/base.py
smallaxe/training/classifiers.py
smallaxe/training/random_forest.py
smallaxe/training/regressors.py
smallaxe/training/mixins/__init__.py
smallaxe/training/mixins/metadata_mixin.py
smallaxe/training/mixins/param_mixin.py
smallaxe/training/mixins/persistence_mixin.py
smallaxe/training/mixins/spark_model_mixin.py
smallaxe/training/mixins/validation_mixin.py
smallaxe/viz/__init__.py
smallaxe-0.6.1.dist-info/licenses/LICENSE
smallaxe-0.6.1.dist-info/METADATA
smallaxe-0.6.1.dist-info/WHEEL
smallaxe-0.6.1.dist-info/top_level.txt
smallaxe-0.6.1.dist-info/RECORD
