Metadata-Version: 2.4
Name: smallaxe
Version: 0.6.1
Summary: A PySpark MLOps library for simplified model training and optimization
Author: Henok Yemam
License: MIT
Project-URL: Homepage, https://github.com/henokyemam/smallaxe
Project-URL: Repository, https://github.com/henokyemam/smallaxe
Project-URL: Issues, https://github.com/henokyemam/smallaxe/issues
Keywords: pyspark,mlops,machine-learning,spark,xgboost,lightgbm,catboost
Classifier: Development Status :: 3 - Alpha
Classifier: Intended Audience :: Developers
Classifier: Intended Audience :: Science/Research
Classifier: License :: OSI Approved :: MIT License
Classifier: Operating System :: OS Independent
Classifier: Programming Language :: Python :: 3
Classifier: Programming Language :: Python :: 3.8
Classifier: Programming Language :: Python :: 3.9
Classifier: Programming Language :: Python :: 3.10
Classifier: Programming Language :: Python :: 3.11
Classifier: Programming Language :: Python :: 3.12
Classifier: Topic :: Scientific/Engineering :: Artificial Intelligence
Classifier: Topic :: Software Development :: Libraries :: Python Modules
Requires-Python: <3.13,>=3.8
License-File: LICENSE
Requires-Dist: pyspark<4.0,>=3.3
Requires-Dist: hyperopt>=0.2.7
Requires-Dist: plotly>=5.0.0
Provides-Extra: xgboost
Requires-Dist: xgboost>=1.7.0; extra == "xgboost"
Provides-Extra: lightgbm
Requires-Dist: lightgbm>=3.3.0; extra == "lightgbm"
Requires-Dist: synapse-ml-lightgbm>=1.0.0; extra == "lightgbm"
Provides-Extra: catboost
Requires-Dist: catboost>=1.1.0; extra == "catboost"
Provides-Extra: all
Requires-Dist: smallaxe[xgboost]; extra == "all"
Requires-Dist: smallaxe[lightgbm]; extra == "all"
Requires-Dist: smallaxe[catboost]; extra == "all"
Provides-Extra: dev
Requires-Dist: pytest>=7.0.0; extra == "dev"
Requires-Dist: pytest-spark>=0.6.0; extra == "dev"
Requires-Dist: black>=23.0.0; extra == "dev"
Requires-Dist: ruff>=0.1.0; extra == "dev"
Requires-Dist: mypy>=1.0.0; extra == "dev"
Dynamic: license-file
